<node>
  <type_nodetype>4</type_nodetype>
  <delegated>1</delegated>
  <node_id>2051203</node_id>
  <title>e2nodetools</title>
  <code>if ( $APP-&gt;isEditor($USER) ){
	my $str =&quot;
	&lt;div id='admintools'&gt;
	&lt;h3&gt;Admin Tools&lt;/h3&gt;&quot;;
	
	$str .= htmlcode(&quot;addfirmlink&quot;);
	unless ($$NODE{group} &amp;&amp; @{ $$NODE{group} }){
		$str .= htmlcode(&quot;addnodeforward&quot;)
			.htmlcode('openform')
			.'&lt;fieldset&gt;&lt;legend&gt;Delete nodeshell&lt;/legend&gt;
			Usually you should only delete a nodeshell if it is egregiously offensive
			or was created by mistake. If there is anything else wrong with it,
			you should just correct the spelling.&lt;br&gt;'
			.$query -&gt; submit('sumbit', 'Delete')
			.$query -&gt; checkbox(
				-name =&gt; 'confirmop'
				, value =&gt; 'nuke'
				, label =&gt; 'I really mean this')
			.'&lt;/fieldset&gt;&lt;/form&gt;';
	}else{
		$str .= htmlcode(&quot;ordernode&quot;);
	}

	$str .= htmlcode('openform')
		.'&lt;fieldset&gt;&lt;legend&gt;Change title&lt;/legend&gt;';
		
	my $newTitle = $query-&gt;param('e2node_title');
	if ($newTitle ne $query-&gt;param('oldTitle')){
		# repair node if title has changed
		if ($$NODE{title} eq $newTitle) {
		   htmlcode('repair e2node', $NODE, 'no-reorder');
		   $str .= &quot;Repaired node to rename all contained writeups.&quot;;

		}else{
		# failed rename
			my $reason = getNode($newTitle, 'e2node');
			$str .= $reason
				? linkNode($reason)
				.' already exists. '
				.linkNode(getNode('Magical Writeup Reparenter', 'superdoc')
					, 'Move all writeups &amp;hellip;'
					, {old_e2node_id =&gt; $$NODE{node_id}
						, new_e2node_id =&gt; $$reason{node_id}
						, reparent_all =&gt; 1
					}
				) 
				: 'Ack! Rename failed.';
		}
		$str .= '&lt;br&gt;';
	}

	$str .= htmlcode('textfield', 'title')
		.$query -&gt; hidden(
			-name =&gt; 'oldTitle'
			, value =&gt; $$NODE{title}
			, force =&gt; 1
		)
		.$query -&gt; submit('rename', &quot;Rename&quot;)
		.'&lt;/fieldset&gt;&lt;/form&gt;';

	$str .= htmlcode(&quot;softlock&quot;);
	
	return &quot;$str\n&lt;/div&gt;&quot;;
}
</code>
</node>
