<node>
  <createtime>2002-03-06 23:01:43</createtime>
  <totalvotes>0</totalvotes>
  <node_id>1264746</node_id>
  <htmlcode_id>1264746</htmlcode_id>
  <code>#return &quot;&quot; unless($$USER{title} eq &quot;JayBonci&quot;);
return &quot;&quot; unless(exists($HTMLVARS{'group_gods'}{$$USER{user_id}}));
my $nhid = $DB-&gt;sqlSelect(&quot;nodehelp_id&quot;, &quot;nodehelp&quot;, &quot;nodehelp_id=$$NODE{node_id}&quot;);

my $temp = (($nhid)?(&quot;view help&quot;):(&quot;create help&quot;));
$temp = &quot;(you are viewing help)&quot; if($query-&gt;param('displaytype') eq &quot;help&quot;);
return &quot;&lt;p align=\&quot;right\&quot;&gt;&quot;.linkNode($NODE, $temp, {'displaytype'=&gt;'help'}).&quot;&lt;/p&gt;&quot;;

</code>
  <type_nodetype>4</type_nodetype>
  <author_user>459692</author_user>
  <title>nodehelpadmin</title>
</node>
