<node>
  <nltext></nltext>
  <parent_container>175986</parent_container>
  <icon>http://images.everything2.com/img/statistics.gif</icon>
  <nlgoto>0</nlgoto>
  <lastupdate>1295898892</lastupdate>
  <node_id>838296</node_id>
  <iconHeight>25</iconHeight>
  <type_nodetype>9</type_nodetype>
  <iconWidth>170</iconWidth>
  <nodelet_id>838296</nodelet_id>
  <nlcode>[%
  $$VARS{numwriteups} ||=0;
  $$VARS{IQM} ||=0;
  return &quot;&quot;;
%][{nodeletsection:stat,personal,Yours,,,i}]
[{nodeletsection:stat,fun,Fun Stats,,,i}]
[{nodeletsection:stat,advancement,Old Merit System,,,i}]
</nlcode>
  <title>Statistics</title>
</node>
