<node>
  <node_id>1422277</node_id>
  <type_nodetype>153</type_nodetype>
  <vars>
    <value>470183</value>
    <key>1153392</key>
  </vars>
  <vars>
    <value>470183</value>
    <key>1257725</key>
  </vars>
  <vars>
    <value>474909</value>
    <key>1091242</key>
  </vars>
  <vars>
    <value>470183</value>
    <key>1263106</key>
  </vars>
  <vars>
    <value>470183</value>
    <key>1259143</key>
  </vars>
  <vars>
    <value>470183</value>
    <key>1147570</key>
  </vars>
  <vars>
    <value>470183</value>
    <key>1242410</key>
  </vars>
  <vars>
    <value>470183</value>
    <key>1131857</key>
  </vars>
  <vars>
    <value>470183</value>
    <key>1154248</key>
  </vars>
  <vars>
    <value>470183</value>
    <key>1256941</key>
  </vars>
  <vars>
    <value>470183</value>
    <key>861527</key>
  </vars>
  <vars>
    <value>470183</value>
    <key>1173524</key>
  </vars>
  <vars>
    <value>470183</value>
    <key>1157413</key>
  </vars>
  <vars>
    <value>397402</value>
    <key>822705</key>
  </vars>
  <vars>
    <value>474909</value>
    <key>1091253</key>
  </vars>
  <vars>
    <value>470183</value>
    <key>1157381</key>
  </vars>
  <vars>
    <value>470183</value>
    <key>1156096</key>
  </vars>
  <vars>
    <value>470183</value>
    <key>1251745</key>
  </vars>
  <vars>
    <value>470183</value>
    <key>855431</key>
  </vars>
  <vars>
    <value>470183</value>
    <key>1178852</key>
  </vars>
  <vars>
    <value>470183</value>
    <key>1256403</key>
  </vars>
  <vars>
    <value>470183</value>
    <key>1101671</key>
  </vars>
  <vars>
    <value>470183</value>
    <key>1172980</key>
  </vars>
  <vars>
    <value>470183</value>
    <key>1168812</key>
  </vars>
  <vars>
    <value>470183</value>
    <key>1167721</key>
  </vars>
  <vars>
    <value>470183</value>
    <key>1254859</key>
  </vars>
  <vars>
    <value>470183</value>
    <key>1118812</key>
  </vars>
  <vars>
    <value>470183</value>
    <key>1257491</key>
  </vars>
  <vars>
    <value>470183</value>
    <key>1101663</key>
  </vars>
  <vars>
    <value>474909</value>
    <key>1145166</key>
  </vars>
  <vars>
    <value>470183</value>
    <key>1158427</key>
  </vars>
  <vars>
    <value>470183</value>
    <key>1162889</key>
  </vars>
  <vars>
    <value>470183</value>
    <key>1262043</key>
  </vars>
  <vars>
    <value>470183</value>
    <key>1076663</key>
  </vars>
  <vars>
    <value>6339</value>
    <key>1215565</key>
  </vars>
  <vars>
    <value>470183</value>
    <key>839979</key>
  </vars>
  <vars>
    <value>470183</value>
    <key>1191581</key>
  </vars>
  <vars>
    <value>406446</value>
    <key>898154</key>
  </vars>
  <vars>
    <value>470183</value>
    <key>1155127</key>
  </vars>
  <vars>
    <value>470183</value>
    <key>1254892</key>
  </vars>
  <vars>
    <value>470183</value>
    <key>1153026</key>
  </vars>
  <vars>
    <value>470183</value>
    <key>1156105</key>
  </vars>
  <vars>
    <value>470183</value>
    <key>1255913</key>
  </vars>
  <vars>
    <value>470183</value>
    <key>1167183</key>
  </vars>
  <vars>
    <value>470183</value>
    <key>1251586</key>
  </vars>
  <vars>
    <value>470183</value>
    <key>1176810</key>
  </vars>
  <vars>
    <value>470183</value>
    <key>1158439</key>
  </vars>
  <vars>
    <value>470183</value>
    <key>1121567</key>
  </vars>
  <vars>
    <value>470183</value>
    <key>1147480</key>
  </vars>
  <vars>
    <value>470183</value>
    <key>1122166</key>
  </vars>
  <vars>
    <value>470183</value>
    <key>1117274</key>
  </vars>
  <vars>
    <value>470183</value>
    <key>1144104</key>
  </vars>
  <vars>
    <value>470183</value>
    <key>1147524</key>
  </vars>
  <vars>
    <value>470183</value>
    <key>1163510</key>
  </vars>
  <vars>
    <value>470183</value>
    <key>1171457</key>
  </vars>
  <vars>
    <value>470183</value>
    <key>1254863</key>
  </vars>
  <vars>
    <value>470183</value>
    <key>1176730</key>
  </vars>
  <vars>
    <value>470183</value>
    <key>1156104</key>
  </vars>
  <vars>
    <value>406446</value>
    <key>1178351</key>
  </vars>
  <vars>
    <value>470183</value>
    <key>1147470</key>
  </vars>
  <vars>
    <value>470183</value>
    <key>1166526</key>
  </vars>
  <vars>
    <value>470183</value>
    <key>1101655</key>
  </vars>
  <vars>
    <value>470183</value>
    <key>1118951</key>
  </vars>
  <vars>
    <value>470183</value>
    <key>1121226</key>
  </vars>
  <vars>
    <value>470183</value>
    <key>1254872</key>
  </vars>
  <vars>
    <value>470183</value>
    <key>1129411</key>
  </vars>
  <vars>
    <value>470183</value>
    <key>1241839</key>
  </vars>
  <vars>
    <value>470183</value>
    <key>1128377</key>
  </vars>
  <vars>
    <value>470183</value>
    <key>1157506</key>
  </vars>
  <vars>
    <value>470183</value>
    <key>1164315</key>
  </vars>
  <vars>
    <value>470183</value>
    <key>1156529</key>
  </vars>
  <vars>
    <value>470183</value>
    <key>850779</key>
  </vars>
  <title>previous godly holdings</title>
</node>
