<node>
  <doctext>&lt;br /&gt;&lt;br /&gt;

&lt;p align=&quot;center&quot;&gt;
  &lt;h3&gt;[%
    my @sayings = (
      'State of the arts',
      'We remember the Alamo',
      'Houston, we have a problem',
      'Drive friendly - the Texas way'
    );
    $sayings[int(rand(@sayings))];
  %]&lt;/h3&gt;
&lt;/p&gt;

&lt;br /&gt;&lt;br /&gt;</doctext>
  <totalvotes>0</totalvotes>
  <createtime>2003-03-17 03:36:45</createtime>
  <node_id>1442900</node_id>
  <edittime>0000-00-00 00:00:00</edittime>
  <type_nodetype>16</type_nodetype>
  <document_id>1442900</document_id>
  <title>lonestars</title>
</node>
