<node>
  <parent_container>0</parent_container>
  <pagetype_nodetype>1786405</pagetype_nodetype>
  <core>0</core>
  <page>[%
my $out = parseCode($$NODE{doctext});
$out =~ s/^\s+//mg unless exists($HTMLVARS{'group_edev'}{$$USER{node_id}});
return $out;
%]</page>
  <reputation>0</reputation>
  <lockedby_user>0</lockedby_user>
  <createtime>2006-02-13 16:41:43</createtime>
  <locktime>0000-00-00 00:00:00</locktime>
  <totalvotes>0</totalvotes>
  <htmlpage_id>1786408</htmlpage_id>
  <hits>0</hits>
  <node_id>1786408</node_id>
  <type_nodetype>5</type_nodetype>
  <displaytype>display</displaytype>
  <author_user>1312198</author_user>
  <package>0</package>
  <ownedby_theme>0</ownedby_theme>
  <title>jscript display page</title>
  <mimetype>text/javascript</mimetype>
</node>
