<node>
  <type_nodetype>451267</type_nodetype>
  <doctext>&lt;COOLEDNODES&gt;&lt;INFO sitename=&quot;Everything2&quot; site=&quot;http://everything2.com&quot; servertime=&quot;Sun Nov  9 03:30:09 2014&quot;&gt;Rendered by the Cool Nodes XML Ticker&lt;/INFO&gt;
	&lt;cooled cooledby_user=&quot;mad girl's love song&quot; node_id=&quot;2116636&quot; parent_e2node=&quot;2047274&quot; author_user=&quot;Estelore&quot;&gt;noli nothis permittere te terere&lt;/cooled&gt;
	&lt;cooled cooledby_user=&quot;Auspice&quot; node_id=&quot;1852054&quot; parent_e2node=&quot;1852053&quot; author_user=&quot;Angela&quot;&gt;drop of red ink in a water glass&lt;/cooled&gt;
	&lt;cooled cooledby_user=&quot;Bitriot&quot; node_id=&quot;2048595&quot; parent_e2node=&quot;2048596&quot; author_user=&quot;Arreter&quot;&gt;Mary-Sue Syndrome&lt;/cooled&gt;
	&lt;cooled cooledby_user=&quot;lizardinlaw&quot; node_id=&quot;2116654&quot; parent_e2node=&quot;2116635&quot; author_user=&quot;AudieMcCall&quot;&gt;November 8, 2014&lt;/cooled&gt;
	&lt;cooled cooledby_user=&quot;Jet-Poop&quot; node_id=&quot;2116095&quot; parent_e2node=&quot;2116551&quot; author_user=&quot;Apollyon&quot;&gt;Echomimetic&lt;/cooled&gt;
	&lt;cooled cooledby_user=&quot;Jet-Poop&quot; node_id=&quot;2116555&quot; parent_e2node=&quot;2116556&quot; author_user=&quot;AudieMcCall&quot;&gt;She Spoke to the Dead&lt;/cooled&gt;
	&lt;cooled cooledby_user=&quot;Jet-Poop&quot; node_id=&quot;2116565&quot; parent_e2node=&quot;2116561&quot; author_user=&quot;Estelore&quot;&gt;Fallen London&lt;/cooled&gt;
	&lt;cooled cooledby_user=&quot;moeyz&quot; node_id=&quot;2116560&quot; parent_e2node=&quot;2116536&quot; author_user=&quot;haqiqat&quot;&gt;November 5, 2014&lt;/cooled&gt;
	&lt;cooled cooledby_user=&quot;Pandeism Fish&quot; node_id=&quot;2115186&quot; parent_e2node=&quot;789917&quot; author_user=&quot;Hazelnut&quot;&gt;I'd love to go back to the late 80's and tell them about our time&lt;/cooled&gt;
	&lt;cooled cooledby_user=&quot;per ou&quot; node_id=&quot;1195144&quot; parent_e2node=&quot;531233&quot; author_user=&quot;O-Swirl&quot;&gt;Tracy Chapman&lt;/cooled&gt;
	&lt;cooled cooledby_user=&quot;Auspice&quot; node_id=&quot;2116620&quot; parent_e2node=&quot;2116621&quot; author_user=&quot;andycyca&quot;&gt;One million words&lt;/cooled&gt;
	&lt;cooled cooledby_user=&quot;etouffee&quot; node_id=&quot;2116652&quot; parent_e2node=&quot;2004006&quot; author_user=&quot;moeyz&quot;&gt;Trace a map along her arm&lt;/cooled&gt;
	&lt;cooled cooledby_user=&quot;moeyz&quot; node_id=&quot;2115651&quot; parent_e2node=&quot;2115650&quot; author_user=&quot;Tem42&quot;&gt;The Day I Swapped My Dad for Two Goldfish&lt;/cooled&gt;
	&lt;cooled cooledby_user=&quot;lizardinlaw&quot; node_id=&quot;783566&quot; parent_e2node=&quot;783550&quot; author_user=&quot;The Custodian&quot;&gt;The Aging Video Warrior&lt;/cooled&gt;
	&lt;cooled cooledby_user=&quot;decoy hunches&quot; node_id=&quot;2107410&quot; parent_e2node=&quot;2098637&quot; author_user=&quot;Estelore&quot;&gt;Eros rose, sore.&lt;/cooled&gt;

&lt;/COOLEDNODES&gt;</doctext>
  <node_id>1101708</node_id>
  <title>Cool Nodes XML Ticker</title>
</node>
