<node>
  <doctext>So it occurs to me that you guys are editors, and your guys are editing a database, let's have some more powerful tools.  This will show you writeups in our database that either don't conform to what we'd like to see in a writeup, or could use to have an editor look at them (no votes, under 20, etc).  You may not want to deal with the broken items, but some of the other items such as the linkless ones, could use to be updated perhaps.&lt;br&gt;&lt;br&gt;
&lt;p align=&quot;right&quot;&gt;Further documentation in [Editors: Node test automation]&lt;/p&gt;
&lt;table&gt;&lt;tr bgcolor=&quot;#DDDDDD&quot;&gt;&lt;td&gt;&lt;b&gt;Test Name&lt;/b&gt;&lt;/td&gt;&lt;td&gt;&lt;b&gt;Applies to:&lt;/b&gt;&lt;/td&gt;&lt;td&gt;&lt;b&gt; Pass/FAIL&lt;/b&gt;&lt;/td&gt;&lt;td width=&quot;200&quot;&gt;&lt;b&gt;Description&lt;/b&gt;&lt;/td&gt;&lt;td&gt;&lt;b&gt;Active?&lt;/b&gt;&lt;/td&gt;&lt;/tr&gt;
[%
 #return &quot;WORKING ON IT.&quot; unless(isGod($USER));
my $csr = $DB-&gt;sqlSelectMany('node_id','node',&quot;type_nodetype=&quot;.getId(getType('nodetest')).' ORDER by title');

my $str = '';

while(my $row = $csr-&gt;fetchrow_hashref())
{

  my $npass = $DB-&gt;sqlSelect('count(*)', 'nodetestresult', &quot;nodetestresult_test=$$row{node_id} and nodetestresult_pass=1&quot;);

  my $nfail = $DB-&gt;sqlSelect('count(*)', 'nodetestresult', &quot;nodetestresult_test=$$row{node_id} and nodetestresult_pass=0&quot;);

  my $nodetest = getNodeById($$row{node_id});

  $str .= '&lt;tr&gt;&lt;td&gt;'.linkNode($nodetest,$$nodetest{title}).'&lt;/td&gt;';
  my $applto = ($$nodetest{nodetest_appliesto})?(getNodeById($$nodetest{nodetest_appliesto})-&gt;{title}):(&quot;&lt;i&gt;none&lt;/i&gt;&quot;);
  #$applto ||= &quot;&lt;i&gt;none&lt;/i&gt;&quot;;
  $str .=&quot;&lt;td&gt;$applto&lt;/td&gt;&quot;;
  $str .=&quot;&lt;td&gt;$npass/$nfail&lt;/td&gt;&lt;td&gt;&quot;.$$nodetest{nodetest_description}.'&lt;/td&gt;&lt;td&gt;&lt;b&gt;';

  if($$nodetest{nodetest_active} == 1){$str.='yes';}
     else{$str.='no';}

  $str .= '&lt;/b&gt;&lt;/td&gt;&lt;/tr&gt;';

}

return $str;

%]
&lt;/table&gt;</doctext>
  <createtime>2002-05-27 10:10:00</createtime>
  <totalvotes>0</totalvotes>
  <node_id>1308790</node_id>
  <edittime>0000-00-00 00:00:00</edittime>
  <type_nodetype>1144104</type_nodetype>
  <document_id>1308790</document_id>
  <author_user>459692</author_user>
  <title>Robotic Editor Shack</title>
</node>
